{
  "folder": "PEMLuhC7aYMz4s84",
  "name": "Stubborn Rage",
  "type": "feature",
  "_id": "f4RB4Mgbi4g39Tha",
  "img": "icons/environment/people/charge.webp",
  "system": {
    "activities": {},
    "uses": {
      "spent": 0,
      "consumeQuantity": false,
      "recovery": [],
      "min": "",
      "max": ""
    },
    "advancement": {},
    "description": {
      "value": "<p>Your rage ends only when its duration expires, you fall unconscious, or you choose to end it.</p>",
      "source": {}
    },
    "restriction": {
      "filters": [],
      "requireAll": true
    },
    "type": {
      "category": "class",
      "value": "heroicBoon"
    },
    "overrides": {
      "proficiency": null
    },
    "identifier": {
      "value": "stubborn-rage",
      "associated": "barbarian"
    },
    "level": {
      "value": null
    }
  },
  "effects": [],
  "sort": 0,
  "ownership": {
    "default": 0
  },
  "flags": {},
  "_stats": {
    "systemId": "black-flag",
    "systemVersion": "0.9.031",
    "coreVersion": "12.328",
    "createdTime": 1717383339055,
    "modifiedTime": 1717385982109,
    "lastModifiedBy": "blackflag0000000",
    "duplicateSource": null
  },
  "_key": "!items!f4RB4Mgbi4g39Tha"
}
