{
  "type": "gear",
  "name": "Gauntlets of Ogre Power",
  "system": {
    "type": {
      "category": "wondrousItem"
    },
    "rarity": "uncommon",
    "price": {
      "value": 2000,
      "denomination": "gp"
    },
    "attunement": {
      "value": "required",
      "requirement": ""
    },
    "description": {
      "value": "<p>Your STR score is 19 while you wear these gauntlets. They have no effect on you if your STR is already 19 or higher.</p>",
      "source": {
        "fallback": ""
      }
    },
    "activities": {},
    "uses": {
      "spent": 0,
      "consumeQuantity": false,
      "recovery": [],
      "min": "",
      "max": ""
    },
    "container": null,
    "quantity": 1,
    "weight": {
      "value": 0,
      "units": "pound"
    },
    "properties": []
  },
  "_id": "HNFIUaTXTfmM0MhT",
  "img": "systems/black-flag/artwork/types/gear.svg",
  "effects": [],
  "folder": "PNS3OPopAxnlSN4O",
  "sort": 0,
  "ownership": {
    "default": 0
  },
  "flags": {},
  "_stats": {
    "duplicateSource": null,
    "coreVersion": "12.331",
    "systemId": "black-flag",
    "systemVersion": "0.10.042",
    "createdTime": 1724984840337,
    "modifiedTime": 1724984841895,
    "lastModifiedBy": "blackflag0000000"
  },
  "_key": "!items!HNFIUaTXTfmM0MhT"
}
