{
  "type": "feature",
  "name": "Nine Lives Stealer",
  "system": {
    "description": {
      "value": "<p>You gain a +2 bonus to attack and damage rolls made with this magic weapon.</p><p>The sword has [[/r 1d8 + 1]] charges. If you score a critical hit against a creature that has fewer than 100 HP, it must succeed on a [[/save 15 CON]] or be slain instantly as the sword tears its life force from its body (a Construct or an Undead is immune). The sword loses 1 charge if the creature is slain. When the sword has no charges remaining, it loses this property.</p><section class=\"secret\" id=\"secret-SRoLPWSush8hua5K\"><p><strong>Foundry Note</strong></p><p><em>Weapon (Any Sword), Very Rare, 8,800 gp (Requires Attunement)</em></p><p>Create the final magic item by selection the appropriate mundane item and dragging an enchantment from the <q>Advancement &amp; Effects</q> tab to that item.</p></section>",
      "source": {
        "fallback": ""
      }
    },
    "activities": {},
    "uses": {
      "spent": 0,
      "consumeQuantity": false,
      "recovery": [],
      "min": "",
      "max": ""
    },
    "advancement": {},
    "restriction": {
      "allowMultipleTimes": false,
      "filters": [],
      "items": [],
      "requireAll": true
    },
    "type": {
      "category": "",
      "value": ""
    },
    "overrides": {
      "proficiency": null
    },
    "identifier": {
      "value": "nine-lives-stealer",
      "associated": ""
    },
    "level": {
      "value": null
    }
  },
  "_id": "N0zoMwOvfIQJ5OSy",
  "img": "systems/black-flag/artwork/types/feature.svg",
  "effects": [],
  "folder": "PNS3OPopAxnlSN4O",
  "sort": 0,
  "ownership": {
    "default": 0
  },
  "flags": {},
  "_stats": {
    "duplicateSource": null,
    "coreVersion": "12.331",
    "systemId": "black-flag",
    "systemVersion": "0.10.046",
    "createdTime": 1726788501344,
    "modifiedTime": 1726788636406,
    "lastModifiedBy": "blackflag0000000"
  },
  "_key": "!items!N0zoMwOvfIQJ5OSy"
}
