{
  "folder": "U9U35Rfs9GqePNlM",
  "name": "Spell Scroll (7th Circle)",
  "type": "consumable",
  "_id": "QSbD2O6ye8dw0KUM",
  "img": "icons/sundries/scrolls/scroll-bound-sealed-black-red.webp",
  "system": {
    "activities": {},
    "uses": {
      "spent": 0,
      "consumeQuantity": true,
      "recovery": [],
      "min": "",
      "max": ""
    },
    "attunement": {},
    "container": null,
    "price": {
      "value": 2500,
      "denomination": "gp"
    },
    "quantity": 1,
    "weight": {
      "value": 0,
      "units": "pound"
    },
    "description": {
      "value": "<p>A <em>spell scroll</em> bears the words of a single spell, written in a mystical cipher. You can read the scroll and cast its spell without providing any material components. Casting the spell by reading the scroll requires the spell’s normal casting time. Once the spell is cast, the words on the scroll fade, and it crumbles to dust. If the casting is interrupted, the scroll is not lost.</p><p>The circle of the spell on the scroll determines the spell’s save DC and attack bonus, as well as the scroll’s rarity.</p><p><strong>Save DC:</strong> 18</p><p><strong>Attack Bonus:</strong> +10</p>",
      "source": {}
    },
    "type": {
      "category": "scroll"
    },
    "rarity": "veryRare",
    "properties": [
      "magical"
    ]
  },
  "effects": [],
  "sort": 0,
  "ownership": {
    "default": 0
  },
  "flags": {},
  "_stats": {
    "systemId": "black-flag",
    "systemVersion": "1.2.058",
    "coreVersion": "12.331",
    "createdTime": 1707356507019,
    "modifiedTime": 1735685242000,
    "lastModifiedBy": "blackflag0000000",
    "duplicateSource": null
  },
  "_key": "!items!QSbD2O6ye8dw0KUM"
}
