{
  "folder": "Qp6iGMULneOQXi2M",
  "name": "Channel Divinity: Mark of Thiumph",
  "type": "feature",
  "_id": "WvenH1OyYc2h0Ml3",
  "img": "icons/svg/item-bag.svg",
  "system": {
    "advancement": {},
    "description": {
      "value": "<p>Starting at 3rd level, you can use your Channel Divinity to mystically mark a foe, making them easier to defeat.</p><p>As a bonus action, you present your holy symbol and mystically mark one creature you can see within 30 feet of you. Until the start of your next turn, any creature who attacks a marked creature has advantage on the first attack roll they make against it.</p>",
      "source": "Black Flag Reference Document"
    },
    "identifier": {
      "associated": ""
    },
    "restriction": {
      "filters": []
    },
    "type": {
      "category": "class",
      "value": "channelDivinity"
    },
    "level": {
      "value": null
    },
    "uses": {
      "min": "",
      "max": ""
    }
  },
  "effects": [],
  "sort": 0,
  "ownership": {
    "default": 0
  },
  "flags": {},
  "_stats": {
    "systemId": "black-flag",
    "systemVersion": "0.8.011",
    "coreVersion": "11.315",
    "createdTime": 1700001802960,
    "modifiedTime": 1706658690670,
    "lastModifiedBy": "blackflag0000000"
  },
  "_key": "!items!WvenH1OyYc2h0Ml3"
}
