{
  "folder": "R1awenmjaG5qtAQT",
  "name": "Touch of Luck",
  "type": "talent",
  "img": "icons/sundries/gaming/dice-runed-brown.webp",
  "system": {
    "description": {
      "value": "<p>Fortune’s favor always makes its way back to you. You gain these benefits:</p><ul><li><p>When you would gain 1 Luck as a result of failing an attack roll or save, you instead gain 2 Luck.</p></li><li><p>If you have 5 Luck and would gain a 6th, your Luck total resets to 1d4 + 1.</p></li></ul>",
      "source": {}
    },
    "identifier": {},
    "type": {
      "category": "technical"
    },
    "advancement": {
      "68HoGL2DDGJqvXQG": {
        "type": "property",
        "_id": "68HoGL2DDGJqvXQG",
        "configuration": {
          "changes": [
            {
              "key": "system.attributes.luck.formula",
              "mode": 5,
              "value": "1d4 + 1"
            }
          ]
        },
        "level": {
          "value": 0,
          "classIdentifier": ""
        },
        "flags": {},
        "title": "Touch of Luck",
        "icon": "",
        "hint": "If you have 5 Luck and would gain a 6th, your Luck total resets to 1d4 + 1."
      }
    },
    "restriction": {
      "filters": [],
      "allowMultipleTimes": false
    },
    "uses": {
      "min": "",
      "max": ""
    }
  },
  "effects": [],
  "ownership": {
    "default": 0
  },
  "flags": {},
  "_stats": {
    "systemId": "black-flag",
    "systemVersion": "0.9.029",
    "coreVersion": "12.328",
    "createdTime": 1695925612918,
    "modifiedTime": 1716348912246,
    "lastModifiedBy": "blackflag0000000",
    "duplicateSource": null
  },
  "_id": "a89OU77hOUv438yn",
  "sort": 0,
  "_key": "!items!a89OU77hOUv438yn"
}
