{
  "folder": "sKeJjeNmn8WvUzET",
  "name": "Fiend",
  "type": "subclass",
  "_id": "mRj6X1fs0gxUrh2Y",
  "img": "icons/creatures/unholy/demon-fire-horned-winged-roar.webp",
  "system": {
    "advancement": {
      "YmScXML0rtJl3WmC": {
        "type": "grantFeatures",
        "level": {
          "value": 3
        },
        "_id": "YmScXML0rtJl3WmC",
        "configuration": {
          "enabled": true,
          "pool": [
            {
              "uuid": "Compendium.black-flag.classes.Item.wILbx6Y5rMUAdu0q"
            },
            {
              "uuid": "Compendium.black-flag.classes.Item.uYazv6bvQh4TxGvr"
            }
          ]
        },
        "flags": {}
      },
      "xJ3zPGLz4OGHsp9h": {
        "type": "grantFeatures",
        "level": {
          "value": 7
        },
        "_id": "xJ3zPGLz4OGHsp9h",
        "configuration": {
          "enabled": true,
          "pool": [
            {
              "uuid": "Compendium.black-flag.classes.Item.2wQBLAVVeqPHDvUG"
            }
          ]
        },
        "flags": {}
      },
      "FsptjNsUCvdQBeW8": {
        "type": "grantFeatures",
        "level": {
          "value": 11
        },
        "_id": "FsptjNsUCvdQBeW8",
        "configuration": {
          "enabled": true,
          "pool": [
            {
              "uuid": "Compendium.black-flag.classes.Item.uAVFZaOnHg6JENWc"
            }
          ]
        },
        "flags": {}
      },
      "VTSkp8GafhX5BZUt": {
        "type": "grantFeatures",
        "level": {
          "value": 15
        },
        "_id": "VTSkp8GafhX5BZUt",
        "configuration": {
          "enabled": true,
          "pool": [
            {
              "uuid": "Compendium.black-flag.classes.Item.IZPE9SYK63gT1JW2"
            }
          ]
        },
        "flags": {}
      }
    },
    "description": {
      "value": "<p>Your patron is a greater fiend who holds dominion over lesser demons or devils. Fiendish patrons are uncontestably bound to the forces of evil—though the warlocks they choose rarely are. These patrons often delight in granting power to mortals, even if those mortals openly strive against their destructive aims. Whether these tendencies are exercises in corruption or serve a more nefarious design, few can say.</p>",
      "source": {
        "fallback": "Black Flag Reference Document"
      },
      "short": "Your patron is a greater fiend who holds dominion over lesser demons or devils. Fiendish patrons are uncontestably bound to the forces of evil—though the warlocks they choose rarely are. These patrons often delight in granting power to mortals, even if those mortals openly strive against their destructive aims. Whether these tendencies are exercises in corruption or serve a more nefarious design, few can say.",
      "journal": "Compendium.black-flag.rules.JournalEntry.v66RykFxGIYeGh29.JournalEntryPage.kryxFxs3VKB9FMON"
    },
    "identifier": {
      "value": "fiend",
      "class": "warlock"
    }
  },
  "effects": [],
  "sort": 0,
  "ownership": {
    "default": 0
  },
  "flags": {},
  "_stats": {
    "systemId": "black-flag",
    "systemVersion": "0.9.037",
    "coreVersion": "12.328",
    "createdTime": 1719376985032,
    "modifiedTime": 1720051524774,
    "lastModifiedBy": "blackflag0000000",
    "duplicateSource": null
  },
  "_key": "!items!mRj6X1fs0gxUrh2Y"
}
