{
  "folder": "LMtPAhFY28bApEKC",
  "name": "Favored Foe",
  "type": "feature",
  "_id": "tgPYAORtOXRt73Z8",
  "img": "icons/creatures/unholy/demons-horned-glowing-pink.webp",
  "system": {
    "activities": {
      "y9K8zdBXabQ8msSF": {
        "type": "utility",
        "_id": "y9K8zdBXabQ8msSF",
        "description": "",
        "system": {},
        "activation": {
          "value": null,
          "type": "long",
          "condition": ""
        },
        "consumption": {
          "targets": [],
          "scale": {
            "allowed": false
          }
        },
        "duration": {
          "units": "day",
          "override": false,
          "value": "1"
        },
        "range": {
          "units": ""
        },
        "target": {
          "template": {
            "count": 1,
            "units": "foot",
            "type": ""
          },
          "affects": {
            "choice": false,
            "type": ""
          },
          "override": false
        },
        "uses": {
          "spent": 0,
          "consumeQuantity": false,
          "recovery": [],
          "min": "",
          "max": ""
        },
        "name": "Study Foe",
        "img": ""
      }
    },
    "uses": {
      "spent": 0,
      "consumeQuantity": false,
      "recovery": [],
      "min": "",
      "max": ""
    },
    "advancement": {},
    "description": {
      "value": "<p>As part of a long rest, you can spend time reviewing your research and preparing to face a specific type of monster.</p><p>Choose a type of enemy: Aberration, Beast, Celestial, Construct, Dragon, Elemental, Fey, Fiend, Giant, Monstrosity, Ooze, Plant, or Undead. For 24 hours, creatures of that type have disadvantage on attack rolls against you. You also have advantage on saves against being charmed, frightened, or possessed by them.</p><p>At the end of your next long rest, you can choose the same type of creature or a different creature type as your Favored Foe.</p>",
      "source": {
        "fallback": "Black Flag Reference Document"
      }
    },
    "restriction": {
      "filters": [],
      "requireAll": true
    },
    "type": {
      "category": "class",
      "value": ""
    },
    "overrides": {
      "proficiency": null
    },
    "identifier": {
      "value": "favored-foe",
      "associated": "hunter"
    },
    "level": {
      "value": 7
    }
  },
  "effects": [],
  "sort": 0,
  "ownership": {
    "default": 0
  },
  "flags": {},
  "_stats": {
    "systemId": "black-flag",
    "systemVersion": "0.9.036",
    "coreVersion": "12.328",
    "createdTime": 1718422353436,
    "modifiedTime": 1718728723880,
    "lastModifiedBy": "blackflag0000000",
    "duplicateSource": null
  },
  "_key": "!items!tgPYAORtOXRt73Z8"
}
