{
  "folder": "H5qfE7S5caUYRLdk",
  "name": "Aim",
  "type": "feature",
  "img": "icons/skills/targeting/crosshair-arrowhead-blue.webp",
  "system": {
    "description": {
      "value": "<p><em>Requires Wielding a Ranged or Thrown Weapon</em></p><p>As a bonus action, you take the time to increase the effectiveness of your next ranged weapon attack. Select one target you can see. If you make a ranged weapon attack against that target before the end of your turn, double your PB for the first attack roll.</p>",
      "source": {}
    },
    "identifier": {
      "associated": ""
    },
    "level": {
      "value": 1
    },
    "type": {
      "category": "class",
      "value": "martialAction"
    },
    "advancement": {},
    "restriction": {
      "filters": []
    },
    "activities": {
      "eU1pHRXaXDLySy9i": {
        "type": "utility",
        "_id": "eU1pHRXaXDLySy9i",
        "description": "<p>Select one target you can see. If you make a ranged weapon attack against that target before the end of your turn, double your PB for the first attack roll.</p>",
        "system": {},
        "activation": {
          "type": "bonus",
          "condition": ""
        },
        "consumption": {
          "targets": [],
          "scale": {
            "allowed": false
          }
        },
        "uses": {
          "spent": 0,
          "recovery": [],
          "min": "",
          "max": ""
        },
        "name": "Aim",
        "img": ""
      }
    },
    "uses": {
      "min": "",
      "max": ""
    }
  },
  "effects": [],
  "ownership": {
    "default": 0
  },
  "flags": {},
  "_stats": {
    "systemId": "black-flag",
    "systemVersion": "0.9.026",
    "coreVersion": "12.328",
    "createdTime": 1695231421958,
    "modifiedTime": 1715718106204,
    "lastModifiedBy": "blackflag0000000",
    "duplicateSource": null
  },
  "_id": "BN6OUOe2ZJRtQ9sU",
  "sort": 100000,
  "_key": "!items!BN6OUOe2ZJRtQ9sU"
}
