{
  "folder": "PdqOhpZgC2CpNOFi",
  "name": "Reforge",
  "type": "feature",
  "img": "icons/svg/item-bag.svg",
  "system": {
    "description": {
      "value": "<p>Your people have a deep connection with elemental fire and have learned how to repair forged items with a touch. You know the mending cantrip, and you can cast it as an action. However, you can use this trait to repair objects made only of metal, such as reconnecting two halves of a broken sword.</p>",
      "source": "Player's Guide"
    },
    "identifier": {},
    "level": {
      "value": null
    },
    "type": {
      "category": "heritage"
    },
    "advancement": {},
    "restriction": {
      "filters": []
    }
  },
  "effects": [],
  "ownership": {
    "default": 0
  },
  "flags": {},
  "_stats": {
    "systemId": "black-flag",
    "systemVersion": "0.5.005",
    "coreVersion": "11.315",
    "createdTime": 1695672251746,
    "modifiedTime": 1701130662977,
    "lastModifiedBy": "blackflag0000000"
  },
  "_id": "7glPCTjcm6iffryd",
  "sort": 0,
  "_key": "!items!7glPCTjcm6iffryd"
}
