{
  "folder": "iJIjiGFvx6IqTXvu",
  "name": "Magic Weapon",
  "type": "spell",
  "_id": "6P5eYTRcKoIQFmGu",
  "img": "icons/magic/fire/dagger-rune-enchant-flame-strong-teal.webp",
  "system": {
    "activities": {
      "wsg84t413fzLmgSC": {
        "type": "utility",
        "_id": "wsg84t413fzLmgSC",
        "description": "",
        "system": {},
        "activation": {},
        "consumption": {
          "targets": [],
          "scale": {
            "allowed": false
          }
        },
        "uses": {
          "spent": 0,
          "recovery": [],
          "consumeQuantity": false
        }
      }
    },
    "uses": {
      "spent": 0,
      "consumeQuantity": false,
      "recovery": [],
      "min": "",
      "max": ""
    },
    "description": {
      "value": "<p>You touch a nonmagical weapon. Until the spell ends, that weapon becomes a magic weapon with a +1 bonus to attack rolls and damage rolls.</p><p><em>At Higher Circles.</em> When you cast this spell using a spell slot of 4th circle or higher, the bonus increases to +2. When you use a spell slot of 6th circle or higher, the bonus increases to +3.</p>",
      "source": {
        "fallback": "Black Flag Reference Document"
      },
      "short": "Enchant a weapon for 1 hour."
    },
    "type": {
      "value": "standard"
    },
    "circle": {
      "value": null,
      "base": 2
    },
    "casting": {
      "value": null,
      "type": "bonus",
      "condition": ""
    },
    "components": {
      "required": [
        "verbal",
        "somatic"
      ],
      "material": {
        "cost": null,
        "consumed": false,
        "denomination": "gp"
      }
    },
    "duration": {
      "units": "hour",
      "value": "1"
    },
    "tags": [
      "concentration"
    ],
    "target": {
      "template": {
        "count": 1,
        "units": "foot",
        "type": ""
      },
      "affects": {
        "choice": false,
        "type": "object",
        "count": "1",
        "special": ""
      }
    },
    "range": {
      "units": "touch",
      "special": ""
    },
    "school": "transmutation",
    "source": [
      "arcane",
      "wyrd"
    ]
  },
  "effects": [],
  "sort": 0,
  "ownership": {
    "default": 0
  },
  "flags": {},
  "_stats": {
    "systemId": "black-flag",
    "systemVersion": "0.10.042",
    "coreVersion": "12.330",
    "createdTime": 1706934544057,
    "modifiedTime": 1722985754814,
    "lastModifiedBy": "blackflag0000000",
    "duplicateSource": null
  },
  "_key": "!items!6P5eYTRcKoIQFmGu"
}
