{
  "folder": "iJIjiGFvx6IqTXvu",
  "name": "Prayer of Healing",
  "type": "spell",
  "_id": "EnwWlw6HgPLyogdd",
  "img": "icons/magic/life/heart-hand-gold-green-light.webp",
  "system": {
    "activities": {
      "rwuwSLwy8IgVJXCk": {
        "type": "healing",
        "_id": "rwuwSLwy8IgVJXCk",
        "description": "",
        "system": {
          "healing": {
            "type": "healing",
            "denomination": 8,
            "bonus": "@mod",
            "custom": "",
            "number": 2,
            "scaling": {
              "mode": "whole",
              "formula": ""
            }
          },
          "ability": ""
        },
        "activation": {
          "value": null,
          "type": "",
          "condition": "",
          "primary": true
        },
        "consumption": {
          "targets": [
            {
              "type": "activity",
              "value": "1",
              "scaling": {}
            }
          ],
          "scale": {
            "allowed": false
          }
        },
        "uses": {
          "spent": 0,
          "recovery": [
            {
              "period": "longRest",
              "type": "recoverAll"
            }
          ],
          "min": "",
          "max": "1",
          "consumeQuantity": false
        },
        "name": "",
        "img": ""
      }
    },
    "uses": {
      "spent": 0,
      "consumeQuantity": false,
      "recovery": [],
      "min": "",
      "max": ""
    },
    "description": {
      "value": "<p>Up to six creatures of your choice that you can see within range each regain hit points equal to [[/healing]]{2d8 + your spellcasting ability modifier}. This spell has no effect on Constructs or Undead.</p><p>Once you cast this spell, you can’t do so again until you complete a long rest.</p><p><em>At Higher Circles.</em> As you unlock higher circles, this ritual grows in potency. Once you have access to 3rd-circle spell slots or higher, the healing increases by [[/healing 1d8]]{1d8} for each slot above 3rd.</p>",
      "source": {
        "fallback": "Black Flag Reference Document"
      },
      "short": "Moderate heal to allies."
    },
    "type": {
      "value": "standard"
    },
    "circle": {
      "value": null,
      "base": 2
    },
    "casting": {
      "value": 10,
      "type": "minute",
      "condition": ""
    },
    "components": {
      "required": [
        "verbal"
      ],
      "material": {
        "cost": null,
        "consumed": false,
        "denomination": "gp"
      }
    },
    "duration": {
      "units": "instantaneous"
    },
    "tags": [],
    "target": {
      "template": {
        "count": 1,
        "units": "foot",
        "type": ""
      },
      "affects": {
        "choice": false,
        "type": "creature",
        "count": "6",
        "special": ""
      }
    },
    "range": {
      "units": "foot",
      "value": "30",
      "special": ""
    },
    "school": "evocation",
    "source": [
      "divine"
    ]
  },
  "effects": [],
  "sort": 0,
  "ownership": {
    "default": 0
  },
  "flags": {},
  "_stats": {
    "systemId": "black-flag",
    "systemVersion": "0.10.042",
    "coreVersion": "12.330",
    "createdTime": 1706997232407,
    "modifiedTime": 1723094502496,
    "lastModifiedBy": "blackflag0000000",
    "duplicateSource": null
  },
  "_key": "!items!EnwWlw6HgPLyogdd"
}
