{
  "folder": "iJIjiGFvx6IqTXvu",
  "name": "Spike Growth",
  "type": "spell",
  "_id": "881NeWKz2mfAQ4kT",
  "img": "icons/magic/nature/trap-spikes-thorns-green.webp",
  "system": {
    "activities": {
      "nmQt6MAFPMmfkOvC": {
        "type": "damage",
        "_id": "nmQt6MAFPMmfkOvC",
        "description": "",
        "system": {
          "damage": {
            "allowCritical": false,
            "parts": [
              {
                "number": 2,
                "denomination": 4,
                "bonus": "",
                "custom": {
                  "formula": "",
                  "enabled": false
                },
                "type": "piercing",
                "scaling": {
                  "mode": "",
                  "number": 1
                },
                "additionalTypes": []
              }
            ]
          },
          "effects": []
        },
        "activation": {
          "value": null,
          "type": "action",
          "condition": "",
          "primary": true
        },
        "consumption": {
          "targets": [],
          "scale": {
            "allowed": false
          }
        },
        "duration": {
          "units": "instantaneous",
          "override": false
        },
        "range": {
          "override": false
        },
        "target": {
          "template": {
            "count": 1,
            "contiguous": false,
            "units": "foot"
          },
          "affects": {
            "choice": false
          },
          "override": false
        },
        "uses": {
          "spent": 0,
          "consumeQuantity": false,
          "recovery": [],
          "min": "",
          "max": ""
        },
        "name": "",
        "img": ""
      }
    },
    "uses": {
      "spent": 0,
      "consumeQuantity": false,
      "recovery": [],
      "min": "",
      "max": ""
    },
    "description": {
      "value": "<p>The ground in a 20-foot radius centered on a point within range twists and sprouts hard spikes and thorns. The area becomes difficult terrain for the duration. When a creature moves into or within the area, it takes [[/damage]] damage for every 5 feet it travels.</p><p>The transformation of the ground is camouflaged to look natural. Any creature that can’t see the area at the time the spell is cast must make a [[/check WIS (Perception) dc=@spellcasting.dc]] check against your spell save DC to recognize the terrain as hazardous before entering it.</p>",
      "source": {
        "fallback": "Black Flag Reference Document"
      },
      "short": "Hidden ground deals piercing."
    },
    "type": {
      "value": "standard"
    },
    "circle": {
      "value": null,
      "base": 2
    },
    "casting": {
      "value": null,
      "type": "action",
      "condition": ""
    },
    "components": {
      "required": [
        "verbal",
        "somatic",
        "material"
      ],
      "material": {
        "cost": null,
        "description": "seven sharp thorns or seven sharpened twigs",
        "consumed": false,
        "denomination": "gp"
      }
    },
    "duration": {
      "units": "minute",
      "value": "10"
    },
    "tags": [
      "concentration"
    ],
    "target": {
      "template": {
        "count": 1,
        "units": "foot",
        "type": "sphere",
        "size": "20"
      },
      "affects": {
        "choice": false,
        "type": "creature",
        "count": "",
        "special": ""
      }
    },
    "range": {
      "units": "foot",
      "value": "150",
      "special": ""
    },
    "school": "transmutation",
    "source": [
      "primordial"
    ]
  },
  "effects": [],
  "sort": 0,
  "ownership": {
    "default": 0
  },
  "flags": {},
  "_stats": {
    "systemId": "black-flag",
    "systemVersion": "0.10.042",
    "coreVersion": "12.330",
    "createdTime": 1706997972095,
    "modifiedTime": 1723438289399,
    "lastModifiedBy": "blackflag0000000",
    "duplicateSource": null
  },
  "_key": "!items!881NeWKz2mfAQ4kT"
}
