{
  "folder": "ASbozScOjLlpmkOc",
  "name": "Superior Recovery",
  "type": "feature",
  "_id": "YSKYwaQ03d7tDsn8",
  "img": "icons/sundries/books/book-open-red.webp",
  "system": {
    "activities": {},
    "uses": {
      "spent": 0,
      "consumeQuantity": false,
      "recovery": [],
      "min": "",
      "max": ""
    },
    "advancement": {},
    "description": {
      "value": "<p>When you use your Arcane Recovery feature, you can choose to swap out a number of prepared Arcane spells with different Arcane spells from your spellbook—in addition to recovering Arcane spell slots. You can swap out a number of prepared spells equal to half your PB (rounded down) in this way.</p>",
      "source": {
        "fallback": "Black Flag Reference Document"
      }
    },
    "restriction": {
      "filters": []
    },
    "type": {
      "category": "class",
      "value": ""
    },
    "identifier": {
      "value": "superior-recovery",
      "associated": "wizard"
    },
    "level": {
      "value": 6
    }
  },
  "effects": [],
  "sort": 600000,
  "ownership": {
    "default": 0
  },
  "flags": {},
  "_stats": {
    "systemId": "black-flag",
    "systemVersion": "0.9.026",
    "coreVersion": "11.315",
    "createdTime": 1715742095272,
    "modifiedTime": 1715742579825,
    "lastModifiedBy": "blackflag0000000"
  },
  "_key": "!items!YSKYwaQ03d7tDsn8"
}
