{
  "folder": "JW7MCVevEcSMmi9e",
  "name": "Scale Mail",
  "type": "armor",
  "_id": "lpKzUaG0LmkOqTb0",
  "img": "icons/equipment/chest/breastplate-rivited-red.webp",
  "system": {
    "overrides": {
      "proficiency": null
    },
    "price": {
      "value": 50,
      "denomination": "gp"
    },
    "quantity": 1,
    "weight": {
      "value": 45,
      "units": "pound"
    },
    "description": {
      "value": "",
      "source": {
        "fallback": "Black Flag Reference Document"
      }
    },
    "type": {
      "category": "medium",
      "base": "scaleMail"
    },
    "properties": [
      "noisy"
    ],
    "armor": {
      "value": 14,
      "requiredStrength": null
    },
    "modifier": {
      "min": null,
      "max": null
    },
    "rarity": "",
    "attunement": {
      "value": ""
    }
  },
  "effects": [],
  "sort": 0,
  "ownership": {
    "default": 0
  },
  "flags": {},
  "_stats": {
    "systemId": "black-flag",
    "systemVersion": "0.8.021",
    "coreVersion": "11.315",
    "createdTime": 1701023514103,
    "modifiedTime": 1713283788762,
    "lastModifiedBy": "blackflag0000000"
  },
  "_key": "!items!lpKzUaG0LmkOqTb0"
}
