{
  "folder": "V6ryz9MMBJLcGrft",
  "name": "Bestow Curse",
  "type": "spell",
  "_id": "f1ovNdb57AhbmDUn",
  "img": "icons/magic/unholy/strike-beam-blood-large-red-teal.webp",
  "system": {
    "activities": {
      "svwea43rf5d9PapD": {
        "type": "savingThrow",
        "_id": "svwea43rf5d9PapD",
        "description": "",
        "system": {
          "ability": "wisdom",
          "damage": {
            "parts": []
          },
          "dc": {
            "ability": ""
          }
        },
        "activation": {
          "type": "",
          "condition": ""
        },
        "consumption": {
          "targets": [],
          "scale": {
            "allowed": false
          }
        },
        "uses": {
          "spent": 0,
          "recovery": [],
          "min": "",
          "max": "",
          "consumeQuantity": false
        },
        "name": "",
        "img": "systems/black-flag/artwork/activities/saving-throw.svg"
      }
    },
    "uses": {
      "spent": 0,
      "consumeQuantity": false,
      "recovery": [],
      "min": "",
      "max": ""
    },
    "description": {
      "value": "<p>You touch a creature, and that creature must succeed on a WIS save or become cursed for the duration of the spell. When you cast this spell, choose the nature of the curse from the following options:</p><ul><li><p>Choose one ability. While cursed, the target has disadvantage on ability checks and saves made with that ability.</p></li><li><p>While cursed, the target has disadvantage on attack rolls against you.</p></li><li><p>While cursed, the target must make a WIS save at the start of each of its turns. If it fails, it wastes its action that turn doing nothing.</p></li><li><p>While the target is cursed, your attacks and spells deal an extra 1d8 necrotic damage to the target.</p></li></ul><p>A <em>remove curse</em> spell ends this effect. At the GM’s discretion, you may choose an alternative curse effect, but it should be no more powerful than those described above.</p><p><em>At Higher Circles.</em> When you cast this spell using a spell slot of 4th circle or higher, the duration becomes concentration, up to 10 minutes. If you use a spell slot of 5th circle or higher, the duration is 8 hours (no concentration). If you use a spell slot of 7th circle or higher, the duration is 24 hours (no concentration). If you use a 9th circle spell slot, the spell lasts until dispelled (no concentration).</p>",
      "source": {
        "fallback": "Black Flag Reference Document"
      },
      "short": "Choose a bad effect for a foe."
    },
    "type": {
      "value": "standard"
    },
    "circle": {
      "value": null,
      "base": 3
    },
    "casting": {
      "value": null,
      "type": "action",
      "condition": ""
    },
    "components": {
      "required": [
        "verbal",
        "somatic"
      ],
      "material": {
        "cost": null,
        "consumed": false,
        "denomination": "gp"
      }
    },
    "duration": {
      "units": "minute",
      "value": "1"
    },
    "tags": [
      "concentration"
    ],
    "target": {
      "template": {
        "count": 1,
        "units": "foot",
        "type": ""
      },
      "affects": {
        "choice": false,
        "type": "creature",
        "count": "1",
        "special": ""
      }
    },
    "range": {
      "units": "touch",
      "special": ""
    },
    "school": "necromancy",
    "source": [
      "divine",
      "wyrd"
    ]
  },
  "effects": [],
  "sort": 2400000,
  "ownership": {
    "default": 0
  },
  "flags": {},
  "_stats": {
    "systemId": "black-flag",
    "systemVersion": "0.9.038",
    "coreVersion": "11.315",
    "createdTime": 1706932300677,
    "modifiedTime": 1720234013022,
    "lastModifiedBy": "blackflag0000000"
  },
  "_key": "!items!f1ovNdb57AhbmDUn"
}
